flamme/__init__.py
flamme/analyzer/__init__.py
flamme/analyzer/base.py
flamme/analyzer/choice.py
flamme/analyzer/column.py
flamme/analyzer/content.py
flamme/analyzer/continuous.py
flamme/analyzer/continuous_advanced.py
flamme/analyzer/count_rows.py
flamme/analyzer/discrete.py
flamme/analyzer/dtype.py
flamme/analyzer/duplicate.py
flamme/analyzer/filter.py
flamme/analyzer/frame_summary.py
flamme/analyzer/mapping.py
flamme/analyzer/markdown.py
flamme/analyzer/most_frequent.py
flamme/analyzer/null.py
flamme/analyzer/null_temp.py
flamme/analyzer/null_temp_col.py
flamme/analyzer/toc.py
flamme/ingestor/__init__.py
flamme/ingestor/base.py
flamme/ingestor/clickhouse.py
flamme/ingestor/csv.py
flamme/ingestor/parquet.py
flamme/ingestor/transform.py
flamme/ingestor/vanilla.py
flamme/reporter/__init__.py
flamme/reporter/base.py
flamme/reporter/no_repeat.py
flamme/reporter/utils.py
flamme/reporter/vanilla.py
flamme/schema/__init__.py
flamme/schema/reader/__init__.py
flamme/schema/reader/base.py
flamme/schema/reader/clickhouse.py
flamme/schema/reader/parquet.py
flamme/schema/reader/vanilla.py
flamme/section/__init__.py
flamme/section/base.py
flamme/section/content.py
flamme/section/continuous.py
flamme/section/continuous_advanced.py
flamme/section/continuous_temporal.py
flamme/section/count_rows.py
flamme/section/discrete.py
flamme/section/discrete_temporal.py
flamme/section/dtype.py
flamme/section/duplicate.py
flamme/section/empty.py
flamme/section/frame_summary.py
flamme/section/mapping.py
flamme/section/markdown.py
flamme/section/most_frequent.py
flamme/section/null.py
flamme/section/null_temp.py
flamme/section/null_temp_col.py
flamme/section/toc.py
flamme/section/utils.py
flamme/testing.py
flamme/transformer/__init__.py
flamme/transformer/dataframe/__init__.py
flamme/transformer/dataframe/base.py
flamme/transformer/dataframe/column.py
flamme/transformer/dataframe/datetime.py
flamme/transformer/dataframe/decimal.py
flamme/transformer/dataframe/null.py
flamme-0.0.16.dist-info/LICENSE
flamme-0.0.16.dist-info/METADATA
flamme-0.0.16.dist-info/WHEEL
flamme-0.0.16.dist-info/RECORD
