Metadata-Version: 2.1
Name: flamme
Version: 0.0.16
Summary: A library to generate custom reports of pandas DataFrames
Home-page: https://github.com/durandtibo/flamme
License: BSD-3-Clause
Keywords: pandas,analysis,report
Author: Thibaut Durand
Author-email: durand.tibo+gh@gmail.com
Requires-Python: >=3.9,<3.13
Classifier: Development Status :: 3 - Alpha
Classifier: Intended Audience :: Developers
Classifier: Intended Audience :: Information Technology
Classifier: Intended Audience :: Science/Research
Classifier: License :: OSI Approved :: BSD License
Classifier: Operating System :: POSIX :: Linux
Classifier: Programming Language :: Python :: 3
Classifier: Programming Language :: Python :: 3.9
Classifier: Programming Language :: Python :: 3.10
Classifier: Programming Language :: Python :: 3.11
Classifier: Programming Language :: Python :: 3.12
Classifier: Topic :: Scientific/Engineering
Classifier: Topic :: Software Development :: Libraries
Provides-Extra: all
Requires-Dist: clickhouse-connect (>=0.7.0,<1.0) ; extra == "all"
Requires-Dist: colorlog (>=6.7,<7.0)
Requires-Dist: coola (>=0.2.0,<1.0)
Requires-Dist: jinja2 (>=3.0,<4.0)
Requires-Dist: markdown (>=3.4,<4.0)
Requires-Dist: matplotlib (>=3.6,<4.0)
Requires-Dist: numpy (>=1.23,<3.0)
Requires-Dist: objectory (>=0.1,<0.2)
Requires-Dist: pandas (>=1.4,<3.0)
Requires-Dist: pyarrow (>=10.0,<17.0)
Requires-Dist: scipy (>=1.10,<2.0)
Requires-Dist: tqdm (>=4.65,<5.0)
Project-URL: Repository, https://github.com/durandtibo/flamme
